{"regions":{"0":{"id":0,"team":0,"tiles":["Vector2i(11, 11)","Vector2i(10, 11)","Vector2i(12, 10)","Vector2i(9, 11)"],"units":0},"1":{"id":1,"team":0,"tiles":["Vector2i(7, 9)","Vector2i(6, 9)","Vector2i(8, 9)","Vector2i(5, 9)"],"units":0},"2":{"id":2,"team":3,"tiles":["Vector2i(10, 1)","Vector2i(9, 1)","Vector2i(8, 1)","Vector2i(11, 1)","Vector2i(12, 1)"],"units":0},"3":{"id":3,"team":0,"tiles":["Vector2i(7, 1)","Vector2i(6, 1)","Vector2i(5, 1)","Vector2i(5, 2)"],"units":0},"4":{"id":4,"team":0,"tiles":["Vector2i(11, 13)","Vector2i(12, 12)","Vector2i(10, 13)"],"units":0},"5":{"id":5,"team":0,"tiles":["Vector2i(3, 3)","Vector2i(2, 4)","Vector2i(1, 5)"],"units":0},"6":{"id":6,"team":0,"tiles":["Vector2i(7, 6)","Vector2i(8, 6)","Vector2i(6, 6)","Vector2i(9, 6)"],"units":0},"7":{"id":7,"team":0,"tiles":["Vector2i(11, 6)","Vector2i(11, 7)","Vector2i(10, 6)","Vector2i(12, 6)"],"units":0},"8":{"id":8,"team":1,"tiles":["Vector2i(0, 8)","Vector2i(0, 7)","Vector2i(-1, 9)","Vector2i(0, 6)"],"units":0},"9":{"id":9,"team":0,"tiles":["Vector2i(14, 4)","Vector2i(13, 4)","Vector2i(13, 5)","Vector2i(13, 6)","Vector2i(13, 7)","Vector2i(13, 8)"],"units":0},"10":{"id":10,"team":0,"tiles":["Vector2i(3, 11)","Vector2i(3, 10)","Vector2i(2, 11)","Vector2i(4, 9)","Vector2i(4, 11)","Vector2i(5, 11)","Vector2i(4, 8)"],"units":0},"11":{"id":11,"team":0,"tiles":["Vector2i(16, 2)","Vector2i(16, 1)","Vector2i(17, 1)","Vector2i(18, 1)","Vector2i(18, 2)","Vector2i(15, 3)"],"units":0},"12":{"id":12,"team":0,"tiles":["Vector2i(9, 4)","Vector2i(8, 4)","Vector2i(10, 4)"],"units":0},"13":{"id":13,"team":2,"tiles":["Vector2i(14, 9)","Vector2i(15, 8)","Vector2i(15, 7)"],"units":0},"14":{"id":14,"team":0,"tiles":["Vector2i(3, 6)","Vector2i(2, 7)","Vector2i(2, 8)","Vector2i(1, 9)","Vector2i(1, 10)"],"units":0},"15":{"id":15,"team":0,"tiles":["Vector2i(-1, 11)","Vector2i(-1, 12)","Vector2i(-1, 10)"],"units":0},"16":{"id":16,"team":0,"tiles":["Vector2i(1, 12)","Vector2i(0, 12)"],"units":0},"17":{"id":17,"team":0,"tiles":["Vector2i(17, 3)","Vector2i(16, 4)"],"units":0},"18":{"id":18,"team":0,"tiles":["Vector2i(8, 11)","Vector2i(7, 11)","Vector2i(6, 11)"],"units":0},"19":{"id":19,"team":0,"tiles":["Vector2i(13, 1)","Vector2i(14, 1)"],"units":0},"20":{"id":20,"team":0,"tiles":["Vector2i(8, 13)","Vector2i(9, 13)"],"units":0},"21":{"id":21,"team":0,"tiles":["Vector2i(13, 9)"],"units":0},"22":{"id":22,"team":4,"tiles":["Vector2i(7, 13)","Vector2i(6, 13)","Vector2i(5, 13)"],"units":0},"23":{"id":23,"team":0,"tiles":["Vector2i(11, 8)","Vector2i(10, 9)"],"units":0},"24":{"id":24,"team":0,"tiles":["Vector2i(5, 4)","Vector2i(4, 5)","Vector2i(5, 3)"],"units":0},"25":{"id":25,"team":0,"tiles":["Vector2i(5, 7)"],"units":0},"26":{"id":26,"team":0,"tiles":["Vector2i(1, 13)","Vector2i(2, 13)"],"units":0},"27":{"id":27,"team":0,"tiles":["Vector2i(9, 9)"],"units":0},"28":{"id":28,"team":0,"tiles":["Vector2i(11, 4)","Vector2i(12, 4)"],"units":0},"29":{"id":29,"team":0,"tiles":["Vector2i(6, 4)","Vector2i(7, 4)"],"units":0},"30":{"id":30,"team":0,"tiles":["Vector2i(2, 10)"],"units":0},"31":{"id":31,"team":0,"tiles":["Vector2i(4, 13)","Vector2i(3, 13)"],"units":0},"32":{"id":32,"team":0,"tiles":["Vector2i(15, 5)","Vector2i(15, 6)"],"units":0},"33":{"id":33,"team":0,"tiles":["Vector2i(4, 2)"],"units":0},"34":{"id":34,"team":0,"tiles":["Vector2i(15, 1)"],"units":0},"35":{"id":35,"team":0,"tiles":["Vector2i(13, 11)","Vector2i(14, 10)"],"units":0}},"teams":[1,2,3,4],"tiles":{"Vector2i(-1, 10)":{"borders":{"0":true,"2":false,"6":true,"8":true,"10":true,"14":true},"coords":"Vector2i(-1, 10)","region":15,"team":0},"Vector2i(-1, 11)":{"borders":{"0":true,"2":false,"6":true,"8":true,"10":false,"14":true},"coords":"Vector2i(-1, 11)","region":15,"team":0},"Vector2i(-1, 12)":{"borders":{"0":true,"2":true,"6":true,"8":true,"10":false,"14":true},"coords":"Vector2i(-1, 12)","region":15,"team":0},"Vector2i(-1, 9)":{"borders":{"0":true,"2":true,"6":true,"8":true,"10":true,"14":false},"coords":"Vector2i(-1, 9)","region":8,"team":1},"Vector2i(0, 12)":{"borders":{"0":false,"2":true,"6":true,"8":true,"10":true,"14":true},"coords":"Vector2i(0, 12)","region":16,"team":0},"Vector2i(0, 6)":{"borders":{"0":true,"2":false,"6":true,"8":true,"10":true,"14":true},"coords":"Vector2i(0, 6)","region":8,"team":1},"Vector2i(0, 7)":{"borders":{"0":true,"2":false,"6":true,"8":true,"10":false,"14":true},"coords":"Vector2i(0, 7)","region":8,"team":1},"Vector2i(0, 8)":{"borders":{"0":true,"2":true,"6":false,"8":true,"10":false,"14":true},"coords":"Vector2i(0, 8)","region":8,"team":1},"Vector2i(1, 10)":{"borders":{"0":true,"2":true,"6":true,"8":true,"10":false,"14":true},"coords":"Vector2i(1, 10)","region":14,"team":0},"Vector2i(1, 12)":{"borders":{"0":true,"2":true,"6":true,"8":false,"10":true,"14":true},"coords":"Vector2i(1, 12)","region":16,"team":0},"Vector2i(1, 13)":{"borders":{"0":false,"2":true,"6":true,"8":true,"10":true,"14":true},"coords":"Vector2i(1, 13)","region":26,"team":0},"Vector2i(1, 5)":{"borders":{"0":true,"2":true,"6":true,"8":true,"10":true,"14":false},"coords":"Vector2i(1, 5)","region":5,"team":0},"Vector2i(1, 9)":{"borders":{"0":true,"2":false,"6":true,"8":true,"10":true,"14":false},"coords":"Vector2i(1, 9)","region":14,"team":0},"Vector2i(10, 1)":{"borders":{"0":false,"2":true,"6":true,"8":false,"10":true,"14":true},"coords":"Vector2i(10, 1)","region":2,"team":3},"Vector2i(10, 11)":{"borders":{"0":false,"2":true,"6":true,"8":false,"10":true,"14":true},"coords":"Vector2i(10, 11)","region":0,"team":0},"Vector2i(10, 13)":{"borders":{"0":false,"2":true,"6":true,"8":true,"10":true,"14":true},"coords":"Vector2i(10, 13)","region":4,"team":0},"Vector2i(10, 4)":{"borders":{"0":true,"2":true,"6":true,"8":false,"10":true,"14":true},"coords":"Vector2i(10, 4)","region":12,"team":0},"Vector2i(10, 6)":{"borders":{"0":false,"2":true,"6":true,"8":true,"10":true,"14":true},"coords":"Vector2i(10, 6)","region":7,"team":0},"Vector2i(10, 9)":{"borders":{"0":true,"2":true,"6":true,"8":true,"10":true,"14":false},"coords":"Vector2i(10, 9)","region":23,"team":0},"Vector2i(11, 1)":{"borders":{"0":false,"2":true,"6":true,"8":false,"10":true,"14":true},"coords":"Vector2i(11, 1)","region":2,"team":3},"Vector2i(11, 11)":{"borders":{"0":true,"2":true,"6":true,"8":false,"10":true,"14":false},"coords":"Vector2i(11, 11)","region":0,"team":0},"Vector2i(11, 13)":{"borders":{"0":true,"2":true,"6":true,"8":false,"10":true,"14":false},"coords":"Vector2i(11, 13)","region":4,"team":0},"Vector2i(11, 4)":{"borders":{"0":false,"2":true,"6":true,"8":true,"10":true,"14":true},"coords":"Vector2i(11, 4)","region":28,"team":0},"Vector2i(11, 6)":{"borders":{"0":false,"2":false,"6":true,"8":false,"10":true,"14":true},"coords":"Vector2i(11, 6)","region":7,"team":0},"Vector2i(11, 7)":{"borders":{"0":true,"2":true,"6":true,"8":true,"10":false,"14":false},"coords":"Vector2i(11, 7)","region":7,"team":0},"Vector2i(11, 8)":{"borders":{"0":true,"2":true,"6":false,"8":true,"10":true,"14":true},"coords":"Vector2i(11, 8)","region":23,"team":0},"Vector2i(12, 1)":{"borders":{"0":true,"2":true,"6":true,"8":false,"10":true,"14":true},"coords":"Vector2i(12, 1)","region":2,"team":3},"Vector2i(12, 10)":{"borders":{"0":true,"2":true,"6":false,"8":true,"10":true,"14":true},"coords":"Vector2i(12, 10)","region":0,"team":0},"Vector2i(12, 12)":{"borders":{"0":true,"2":true,"6":false,"8":true,"10":true,"14":true},"coords":"Vector2i(12, 12)","region":4,"team":0},"Vector2i(12, 4)":{"borders":{"0":true,"2":true,"6":true,"8":false,"10":true,"14":true},"coords":"Vector2i(12, 4)","region":28,"team":0},"Vector2i(12, 6)":{"borders":{"0":true,"2":true,"6":false,"8":false,"10":true,"14":true},"coords":"Vector2i(12, 6)","region":7,"team":0},"Vector2i(13, 1)":{"borders":{"0":false,"2":true,"6":true,"8":true,"10":true,"14":true},"coords":"Vector2i(13, 1)","region":19,"team":0},"Vector2i(13, 11)":{"borders":{"0":true,"2":true,"6":true,"8":true,"10":true,"14":false},"coords":"Vector2i(13, 11)","region":35,"team":0},"Vector2i(13, 4)":{"borders":{"0":false,"2":false,"6":true,"8":true,"10":true,"14":true},"coords":"Vector2i(13, 4)","region":9,"team":0},"Vector2i(13, 5)":{"borders":{"0":true,"2":false,"6":true,"8":true,"10":false,"14":false},"coords":"Vector2i(13, 5)","region":9,"team":0},"Vector2i(13, 6)":{"borders":{"0":true,"2":false,"6":true,"8":true,"10":false,"14":true},"coords":"Vector2i(13, 6)","region":9,"team":0},"Vector2i(13, 7)":{"borders":{"0":true,"2":false,"6":true,"8":true,"10":false,"14":true},"coords":"Vector2i(13, 7)","region":9,"team":0},"Vector2i(13, 8)":{"borders":{"0":true,"2":true,"6":true,"8":true,"10":false,"14":true},"coords":"Vector2i(13, 8)","region":9,"team":0},"Vector2i(13, 9)":{"borders":{"0":true,"2":true,"6":true,"8":true,"10":true,"14":true},"coords":"Vector2i(13, 9)","region":21,"team":0},"Vector2i(14, 1)":{"borders":{"0":true,"2":true,"6":true,"8":false,"10":true,"14":true},"coords":"Vector2i(14, 1)","region":19,"team":0},"Vector2i(14, 10)":{"borders":{"0":true,"2":true,"6":false,"8":true,"10":true,"14":true},"coords":"Vector2i(14, 10)","region":35,"team":0},"Vector2i(14, 4)":{"borders":{"0":true,"2":true,"6":false,"8":false,"10":true,"14":true},"coords":"Vector2i(14, 4)","region":9,"team":0},"Vector2i(14, 9)":{"borders":{"0":true,"2":true,"6":true,"8":true,"10":true,"14":false},"coords":"Vector2i(14, 9)","region":13,"team":2},"Vector2i(15, 1)":{"borders":{"0":true,"2":true,"6":true,"8":true,"10":true,"14":true},"coords":"Vector2i(15, 1)","region":34,"team":0},"Vector2i(15, 3)":{"borders":{"0":true,"2":true,"6":true,"8":true,"10":true,"14":false},"coords":"Vector2i(15, 3)","region":11,"team":0},"Vector2i(15, 5)":{"borders":{"0":true,"2":false,"6":true,"8":true,"10":true,"14":true},"coords":"Vector2i(15, 5)","region":32,"team":0},"Vector2i(15, 6)":{"borders":{"0":true,"2":true,"6":true,"8":true,"10":false,"14":true},"coords":"Vector2i(15, 6)","region":32,"team":0},"Vector2i(15, 7)":{"borders":{"0":true,"2":false,"6":true,"8":true,"10":true,"14":true},"coords":"Vector2i(15, 7)","region":13,"team":2},"Vector2i(15, 8)":{"borders":{"0":true,"2":true,"6":false,"8":true,"10":false,"14":true},"coords":"Vector2i(15, 8)","region":13,"team":2},"Vector2i(16, 1)":{"borders":{"0":false,"2":false,"6":true,"8":true,"10":true,"14":true},"coords":"Vector2i(16, 1)","region":11,"team":0},"Vector2i(16, 2)":{"borders":{"0":true,"2":true,"6":false,"8":true,"10":false,"14":false},"coords":"Vector2i(16, 2)","region":11,"team":0},"Vector2i(16, 4)":{"borders":{"0":true,"2":true,"6":true,"8":true,"10":true,"14":false},"coords":"Vector2i(16, 4)","region":17,"team":0},"Vector2i(17, 1)":{"borders":{"0":false,"2":true,"6":false,"8":false,"10":true,"14":true},"coords":"Vector2i(17, 1)","region":11,"team":0},"Vector2i(17, 3)":{"borders":{"0":true,"2":true,"6":false,"8":true,"10":true,"14":true},"coords":"Vector2i(17, 3)","region":17,"team":0},"Vector2i(18, 1)":{"borders":{"0":true,"2":false,"6":true,"8":false,"10":true,"14":true},"coords":"Vector2i(18, 1)","region":11,"team":0},"Vector2i(18, 2)":{"borders":{"0":true,"2":true,"6":true,"8":true,"10":false,"14":true},"coords":"Vector2i(18, 2)","region":11,"team":0},"Vector2i(2, 10)":{"borders":{"0":true,"2":true,"6":true,"8":true,"10":true,"14":true},"coords":"Vector2i(2, 10)","region":30,"team":0},"Vector2i(2, 11)":{"borders":{"0":false,"2":true,"6":true,"8":true,"10":true,"14":false},"coords":"Vector2i(2, 11)","region":10,"team":0},"Vector2i(2, 13)":{"borders":{"0":true,"2":true,"6":true,"8":false,"10":true,"14":true},"coords":"Vector2i(2, 13)","region":26,"team":0},"Vector2i(2, 4)":{"borders":{"0":true,"2":true,"6":false,"8":true,"10":true,"14":false},"coords":"Vector2i(2, 4)","region":5,"team":0},"Vector2i(2, 7)":{"borders":{"0":true,"2":false,"6":true,"8":true,"10":true,"14":false},"coords":"Vector2i(2, 7)","region":14,"team":0},"Vector2i(2, 8)":{"borders":{"0":true,"2":true,"6":false,"8":true,"10":false,"14":true},"coords":"Vector2i(2, 8)","region":14,"team":0},"Vector2i(3, 10)":{"borders":{"0":true,"2":false,"6":false,"8":true,"10":true,"14":false},"coords":"Vector2i(3, 10)","region":10,"team":0},"Vector2i(3, 11)":{"borders":{"0":false,"2":true,"6":true,"8":false,"10":false,"14":true},"coords":"Vector2i(3, 11)","region":10,"team":0},"Vector2i(3, 13)":{"borders":{"0":false,"2":true,"6":true,"8":true,"10":true,"14":true},"coords":"Vector2i(3, 13)","region":31,"team":0},"Vector2i(3, 3)":{"borders":{"0":true,"2":true,"6":false,"8":true,"10":true,"14":true},"coords":"Vector2i(3, 3)","region":5,"team":0},"Vector2i(3, 6)":{"borders":{"0":true,"2":true,"6":false,"8":true,"10":true,"14":true},"coords":"Vector2i(3, 6)","region":14,"team":0},"Vector2i(4, 11)":{"borders":{"0":false,"2":true,"6":true,"8":false,"10":true,"14":true},"coords":"Vector2i(4, 11)","region":10,"team":0},"Vector2i(4, 13)":{"borders":{"0":true,"2":true,"6":true,"8":false,"10":true,"14":true},"coords":"Vector2i(4, 13)","region":31,"team":0},"Vector2i(4, 2)":{"borders":{"0":true,"2":true,"6":true,"8":true,"10":true,"14":true},"coords":"Vector2i(4, 2)","region":33,"team":0},"Vector2i(4, 5)":{"borders":{"0":true,"2":true,"6":true,"8":true,"10":true,"14":false},"coords":"Vector2i(4, 5)","region":24,"team":0},"Vector2i(4, 8)":{"borders":{"0":true,"2":false,"6":true,"8":true,"10":true,"14":true},"coords":"Vector2i(4, 8)","region":10,"team":0},"Vector2i(4, 9)":{"borders":{"0":true,"2":true,"6":false,"8":true,"10":false,"14":true},"coords":"Vector2i(4, 9)","region":10,"team":0},"Vector2i(5, 1)":{"borders":{"0":false,"2":false,"6":true,"8":true,"10":true,"14":true},"coords":"Vector2i(5, 1)","region":3,"team":0},"Vector2i(5, 11)":{"borders":{"0":true,"2":true,"6":true,"8":false,"10":true,"14":true},"coords":"Vector2i(5, 11)","region":10,"team":0},"Vector2i(5, 13)":{"borders":{"0":false,"2":true,"6":true,"8":true,"10":true,"14":true},"coords":"Vector2i(5, 13)","region":22,"team":4},"Vector2i(5, 2)":{"borders":{"0":true,"2":true,"6":true,"8":true,"10":false,"14":false},"coords":"Vector2i(5, 2)","region":3,"team":0},"Vector2i(5, 3)":{"borders":{"0":true,"2":false,"6":true,"8":true,"10":true,"14":true},"coords":"Vector2i(5, 3)","region":24,"team":0},"Vector2i(5, 4)":{"borders":{"0":true,"2":true,"6":false,"8":true,"10":false,"14":true},"coords":"Vector2i(5, 4)","region":24,"team":0},"Vector2i(5, 7)":{"borders":{"0":true,"2":true,"6":true,"8":true,"10":true,"14":true},"coords":"Vector2i(5, 7)","region":25,"team":0},"Vector2i(5, 9)":{"borders":{"0":false,"2":true,"6":true,"8":true,"10":true,"14":true},"coords":"Vector2i(5, 9)","region":1,"team":0},"Vector2i(6, 1)":{"borders":{"0":false,"2":true,"6":false,"8":false,"10":true,"14":true},"coords":"Vector2i(6, 1)","region":3,"team":0},"Vector2i(6, 11)":{"borders":{"0":false,"2":true,"6":true,"8":true,"10":true,"14":true},"coords":"Vector2i(6, 11)","region":18,"team":0},"Vector2i(6, 13)":{"borders":{"0":false,"2":true,"6":true,"8":false,"10":true,"14":true},"coords":"Vector2i(6, 13)","region":22,"team":4},"Vector2i(6, 4)":{"borders":{"0":false,"2":true,"6":true,"8":true,"10":true,"14":true},"coords":"Vector2i(6, 4)","region":29,"team":0},"Vector2i(6, 6)":{"borders":{"0":false,"2":true,"6":true,"8":true,"10":true,"14":true},"coords":"Vector2i(6, 6)","region":6,"team":0},"Vector2i(6, 9)":{"borders":{"0":false,"2":true,"6":true,"8":false,"10":true,"14":true},"coords":"Vector2i(6, 9)","region":1,"team":0},"Vector2i(7, 1)":{"borders":{"0":true,"2":true,"6":true,"8":false,"10":true,"14":true},"coords":"Vector2i(7, 1)","region":3,"team":0},"Vector2i(7, 11)":{"borders":{"0":false,"2":true,"6":true,"8":false,"10":true,"14":true},"coords":"Vector2i(7, 11)","region":18,"team":0},"Vector2i(7, 13)":{"borders":{"0":true,"2":true,"6":true,"8":false,"10":true,"14":true},"coords":"Vector2i(7, 13)","region":22,"team":4},"Vector2i(7, 4)":{"borders":{"0":true,"2":true,"6":true,"8":false,"10":true,"14":true},"coords":"Vector2i(7, 4)","region":29,"team":0},"Vector2i(7, 6)":{"borders":{"0":false,"2":true,"6":true,"8":false,"10":true,"14":true},"coords":"Vector2i(7, 6)","region":6,"team":0},"Vector2i(7, 9)":{"borders":{"0":false,"2":true,"6":true,"8":false,"10":true,"14":true},"coords":"Vector2i(7, 9)","region":1,"team":0},"Vector2i(8, 1)":{"borders":{"0":false,"2":true,"6":true,"8":true,"10":true,"14":true},"coords":"Vector2i(8, 1)","region":2,"team":3},"Vector2i(8, 11)":{"borders":{"0":true,"2":true,"6":true,"8":false,"10":true,"14":true},"coords":"Vector2i(8, 11)","region":18,"team":0},"Vector2i(8, 13)":{"borders":{"0":false,"2":true,"6":true,"8":true,"10":true,"14":true},"coords":"Vector2i(8, 13)","region":20,"team":0},"Vector2i(8, 4)":{"borders":{"0":false,"2":true,"6":true,"8":true,"10":true,"14":true},"coords":"Vector2i(8, 4)","region":12,"team":0},"Vector2i(8, 6)":{"borders":{"0":false,"2":true,"6":true,"8":false,"10":true,"14":true},"coords":"Vector2i(8, 6)","region":6,"team":0},"Vector2i(8, 9)":{"borders":{"0":true,"2":true,"6":true,"8":false,"10":true,"14":true},"coords":"Vector2i(8, 9)","region":1,"team":0},"Vector2i(9, 1)":{"borders":{"0":false,"2":true,"6":true,"8":false,"10":true,"14":true},"coords":"Vector2i(9, 1)","region":2,"team":3},"Vector2i(9, 11)":{"borders":{"0":false,"2":true,"6":true,"8":true,"10":true,"14":true},"coords":"Vector2i(9, 11)","region":0,"team":0},"Vector2i(9, 13)":{"borders":{"0":true,"2":true,"6":true,"8":false,"10":true,"14":true},"coords":"Vector2i(9, 13)","region":20,"team":0},"Vector2i(9, 4)":{"borders":{"0":false,"2":true,"6":true,"8":false,"10":true,"14":true},"coords":"Vector2i(9, 4)","region":12,"team":0},"Vector2i(9, 6)":{"borders":{"0":true,"2":true,"6":true,"8":false,"10":true,"14":true},"coords":"Vector2i(9, 6)","region":6,"team":0},"Vector2i(9, 9)":{"borders":{"0":true,"2":true,"6":true,"8":true,"10":true,"14":true},"coords":"Vector2i(9, 9)","region":27,"team":0}}}
